rddl2tf/__init__.py
rddl2tf/utils.py
rddl2tf/compilers/__init__.py
rddl2tf/compilers/compiler.py
rddl2tf/compilers/initializer.py
rddl2tf/compilers/scope.py
rddl2tf/compilers/modes/__init__.py
rddl2tf/compilers/modes/default.py
rddl2tf/compilers/modes/reparameterization.py
rddl2tf/core/__init__.py
rddl2tf/core/fluent.py
rddl2tf/core/fluentscope.py
rddl2tf/core/fluentshape.py
rddl2tf-0.5.13.data/scripts/rddl2tf
tests/__init__.py
tests/test_compiler_default.py
tests/test_compiler_reparameterization.py
tests/test_compilers_initializer.py
tests/test_compilers_scope.py
tests/test_fluent.py
tests/test_fluentscope.py
tests/test_fluentshape.py
rddl2tf-0.5.13.dist-info/LICENSE.txt
rddl2tf-0.5.13.dist-info/METADATA
rddl2tf-0.5.13.dist-info/WHEEL
rddl2tf-0.5.13.dist-info/top_level.txt
rddl2tf-0.5.13.dist-info/RECORD
