Metadata-Version: 2.1
Name: rddl2tf
Version: 0.5.13
Summary: RDDL2TensorFlow compiler.
Home-page: https://github.com/thiagopbueno/rddl2tf
Author: Thiago P. Bueno
Author-email: thiago.pbueno@gmail.com
License: GNU General Public License v3.0
Keywords: rddl,tensorflow,compiler
Platform: UNKNOWN
Classifier: Development Status :: 3 - Alpha
Classifier: Environment :: Console
Classifier: Intended Audience :: Science/Research
Classifier: License :: OSI Approved :: GNU General Public License v3 (GPLv3)
Classifier: Natural Language :: English
Classifier: Operating System :: OS Independent
Classifier: Programming Language :: Python :: 3.6
Classifier: Topic :: Scientific/Engineering :: Artificial Intelligence
Requires-Python: >=3.6
Requires-Dist: tensorflow (<2.0.0)
Requires-Dist: typing
Requires-Dist: pyrddl
Requires-Dist: rddlgym
